GraderPackage/__init__.py
GraderPackage/grader.py
TextGrader-0.1.1.dist-info/METADATA
TextGrader-0.1.1.dist-info/WHEEL
TextGrader-0.1.1.dist-info/top_level.txt
TextGrader-0.1.1.dist-info/RECORD
