Metadata-Version: 2.1
Name: TextGrader
Version: 0.1.1
Summary: UNKNOWN
Home-page: UNKNOWN
License: UNKNOWN
Platform: UNKNOWN
Requires-Python: >=3.9
Requires-Dist: torch
Requires-Dist: transformers
Requires-Dist: tqdm
